network_tools/__init__.py
network_tools/traceroute.py
network_tools-0.0.1.dist-info/LICENSE
network_tools-0.0.1.dist-info/METADATA
network_tools-0.0.1.dist-info/WHEEL
network_tools-0.0.1.dist-info/top_level.txt
network_tools-0.0.1.dist-info/RECORD
